[
    {
        "first_name": "Tammy",
        "last_name": "Alvarez",
        "email": "mathew37@example.net"
    },
    {
        "first_name": "Brandon",
        "last_name": "Anderson",
        "email": "stacyreyes@example.com"
    },
    {
        "first_name": "Mary",
        "last_name": "Austin",
        "email": "walterspatrick@example.com"
    },
    {
        "first_name": "Virginia",
        "last_name": "Austin",
        "email": "robert60@example.org"
    },
    {
        "first_name": "James",
        "last_name": "Bailey",
        "email": "william03@example.com"
    },
    {
        "first_name": "Jennifer",
        "last_name": "Barry",
        "email": "jvasquez@example.net"
    },
    {
        "first_name": "Manuel",
        "last_name": "Blevins",
        "email": "amyhutchinson@example.net"
    },
    {
        "first_name": "Sara",
        "last_name": "Bradley",
        "email": "tallen@example.com"
    },
    {
        "first_name": "Matthew",
        "last_name": "Byrd",
        "email": "tanyawilliams@example.net"
    },
    {
        "first_name": "Allison",
        "last_name": "Casey",
        "email": "alexandra56@example.org"
    },
    {
        "first_name": "Alexander",
        "last_name": "Clark",
        "email": "frankkennedy@example.com"
    },
    {
        "first_name": "Franklin",
        "last_name": "Clark",
        "email": "kaitlyngraham@example.org"
    },
    {
        "first_name": "Shannon",
        "last_name": "Compton",
        "email": "aliciaalexander@example.org"
    },
    {
        "first_name": "Pamela",
        "last_name": "Copeland",
        "email": "thomasgraves@example.net"
    },
    {
        "first_name": "James",
        "last_name": "Cuevas",
        "email": "maria87@example.net"
    },
    {
        "first_name": "Jorge",
        "last_name": "Davis",
        "email": "williamdouglas@example.com"
    },
    {
        "first_name": "Cody",
        "last_name": "Dickerson",
        "email": "cnguyen@example.com"
    },
    {
        "first_name": "Calvin",
        "last_name": "Erickson",
        "email": "danielle21@example.org"
    },
    {
        "first_name": "Erin",
        "last_name": "Farley",
        "email": "williamsjason@example.com"
    },
    {
        "first_name": "Clifford",
        "last_name": "Finley",
        "email": "marshallkevin@example.net"
    },
    {
        "first_name": "Mike",
        "last_name": "Ford",
        "email": "fharrison@example.org"
    },
    {
        "first_name": "David",
        "last_name": "Foster",
        "email": "donna57@example.net"
    },
    {
        "first_name": "Debra",
        "last_name": "Foster",
        "email": "masondaniel@example.org"
    },
    {
        "first_name": "John",
        "last_name": "Foster",
        "email": "agonzales@example.net"
    },
    {
        "first_name": "Danielle",
        "last_name": "Francis",
        "email": "dicksonmelissa@example.com"
    },
    {
        "first_name": "Autumn",
        "last_name": "Gonzales",
        "email": "nwood@example.org"
    },
    {
        "first_name": "Travis",
        "last_name": "Guerra",
        "email": "lewisjack@example.com"
    },
    {
        "first_name": "Carol",
        "last_name": "Hancock",
        "email": "mistyburton@example.org"
    },
    {
        "first_name": "David",
        "last_name": "Harmon",
        "email": "danielle54@example.net"
    },
    {
        "first_name": "Krista",
        "last_name": "Harper",
        "email": "bowerslouis@example.org"
    },
    {
        "first_name": "Lisa",
        "last_name": "Harrington",
        "email": "gweber@example.net"
    },
    {
        "first_name": "Jessica",
        "last_name": "Hawkins",
        "email": "wrodriguez@example.com"
    },
    {
        "first_name": "Judy",
        "last_name": "Hines",
        "email": "sandra41@example.org"
    },
    {
        "first_name": "Ariel",
        "last_name": "Howell",
        "email": "sallymoss@example.org"
    },
    {
        "first_name": "Timothy",
        "last_name": "Ibarra",
        "email": "ojohnson@example.com"
    },
    {
        "first_name": "Erik",
        "last_name": "James",
        "email": "moralesrobert@example.com"
    },
    {
        "first_name": "Natalie",
        "last_name": "Johnson",
        "email": "zachary16@example.com"
    },
    {
        "first_name": "Parker",
        "last_name": "Johnson",
        "email": "ldoyle@example.com"
    },
    {
        "first_name": "Connie",
        "last_name": "Keller",
        "email": "jennifer08@example.com"
    },
    {
        "first_name": "Brittany",
        "last_name": "Kent",
        "email": "taratran@example.com"
    },
    {
        "first_name": "Fernando",
        "last_name": "Kidd",
        "email": "reynoldskatie@example.com"
    },
    {
        "first_name": "Tyler",
        "last_name": "Lane",
        "email": "ndelgado@example.com"
    },
    {
        "first_name": "Natasha",
        "last_name": "Lee",
        "email": "sonia08@example.net"
    },
    {
        "first_name": "Nathan",
        "last_name": "Lopez",
        "email": "yschmidt@example.net"
    },
    {
        "first_name": "Jesse",
        "last_name": "Lowe",
        "email": "terrisharp@example.org"
    },
    {
        "first_name": "Christopher",
        "last_name": "Maddox",
        "email": "vmacdonald@example.net"
    },
    {
        "first_name": "Jason",
        "last_name": "Mann",
        "email": "markgonzales@example.org"
    },
    {
        "first_name": "Alexander",
        "last_name": "Marshall",
        "email": "fadams@example.net"
    },
    {
        "first_name": "Jason",
        "last_name": "Martin",
        "email": "aimeenelson@example.net"
    },
    {
        "first_name": "Melanie",
        "last_name": "Mathews",
        "email": "sking@example.com"
    },
    {
        "first_name": "Denise",
        "last_name": "Medina",
        "email": "cindychambers@example.org"
    },
    {
        "first_name": "Abigail",
        "last_name": "Michael",
        "email": "henrygordon@example.com"
    },
    {
        "first_name": "Gary",
        "last_name": "Moore",
        "email": "jjohnson@example.org"
    },
    {
        "first_name": "Lynn",
        "last_name": "Moore",
        "email": "swansonkenneth@example.org"
    },
    {
        "first_name": "Kimberly",
        "last_name": "Morgan",
        "email": "brandonfernandez@example.com"
    },
    {
        "first_name": "Stephanie",
        "last_name": "Murillo",
        "email": "rebecca17@example.com"
    },
    {
        "first_name": "Joan",
        "last_name": "Myers",
        "email": "owarner@example.org"
    },
    {
        "first_name": "Stephanie",
        "last_name": "Nguyen",
        "email": "connorrollins@example.com"
    },
    {
        "first_name": "Deborah",
        "last_name": "Obrien",
        "email": "whitejoanna@example.net"
    },
    {
        "first_name": "Tiffany",
        "last_name": "Parker",
        "email": "henry64@example.com"
    },
    {
        "first_name": "Blake",
        "last_name": "Parsons",
        "email": "suzanne06@example.net"
    },
    {
        "first_name": "Luis",
        "last_name": "Patel",
        "email": "kimberly38@example.net"
    },
    {
        "first_name": "Casey",
        "last_name": "Price",
        "email": "marklucas@example.net"
    },
    {
        "first_name": "Priscilla",
        "last_name": "Riley",
        "email": "lnash@example.org"
    },
    {
        "first_name": "Duane",
        "last_name": "Rodriguez",
        "email": "mary23@example.org"
    },
    {
        "first_name": "Megan",
        "last_name": "Rosario",
        "email": "madelinefreeman@example.org"
    },
    {
        "first_name": "Gary",
        "last_name": "Russell",
        "email": "andrewjones@example.com"
    },
    {
        "first_name": "Rachel",
        "last_name": "Sanford",
        "email": "emarquez@example.com"
    },
    {
        "first_name": "Cheryl",
        "last_name": "Santana",
        "email": "tmcdowell@example.org"
    },
    {
        "first_name": "Michael",
        "last_name": "Short",
        "email": "kyle72@example.com"
    },
    {
        "first_name": "Kristina",
        "last_name": "Smith",
        "email": "davisjeffrey@example.com"
    },
    {
        "first_name": "Lori",
        "last_name": "Smith",
        "email": "mwillis@example.org"
    },
    {
        "first_name": "Richard",
        "last_name": "Smith",
        "email": "dwilson@example.org"
    },
    {
        "first_name": "Timothy",
        "last_name": "Smith",
        "email": "pbray@example.org"
    },
    {
        "first_name": "Eric",
        "last_name": "Snow",
        "email": "hendersonsarah@example.com"
    },
    {
        "first_name": "Scott",
        "last_name": "Spencer",
        "email": "scole@example.org"
    },
    {
        "first_name": "Ashley",
        "last_name": "Stephenson",
        "email": "joann31@example.com"
    },
    {
        "first_name": "Jennifer",
        "last_name": "Stone",
        "email": "donaldwoods@example.net"
    },
    {
        "first_name": "Brian",
        "last_name": "Stout",
        "email": "gkim@example.com"
    },
    {
        "first_name": "Justin",
        "last_name": "Sullivan",
        "email": "jenkinschristopher@example.org"
    },
    {
        "first_name": "Allen",
        "last_name": "Taylor",
        "email": "carlosmartin@example.org"
    },
    {
        "first_name": "Michele",
        "last_name": "Taylor",
        "email": "robert37@example.net"
    },
    {
        "first_name": "Ronald",
        "last_name": "Torres",
        "email": "johnathan87@example.com"
    },
    {
        "first_name": "Clayton",
        "last_name": "Tran",
        "email": "isnyder@example.com"
    },
    {
        "first_name": "Joseph",
        "last_name": "Turner",
        "email": "jennifer53@example.net"
    },
    {
        "first_name": "Kelsey",
        "last_name": "Tyler",
        "email": "dgreen@example.net"
    },
    {
        "first_name": "Gerald",
        "last_name": "Vasquez",
        "email": "richardpratt@example.org"
    },
    {
        "first_name": "Julie",
        "last_name": "Vega",
        "email": "evanstroy@example.org"
    },
    {
        "first_name": "Shane",
        "last_name": "Vincent",
        "email": "vicki02@example.com"
    },
    {
        "first_name": "Joshua",
        "last_name": "Wagner",
        "email": "jesse79@example.com"
    },
    {
        "first_name": "Jason",
        "last_name": "Ward",
        "email": "christian37@example.org"
    },
    {
        "first_name": "Catherine",
        "last_name": "White",
        "email": "derek71@example.net"
    },
    {
        "first_name": "Charles",
        "last_name": "White",
        "email": "whiteheadshawn@example.net"
    },
    {
        "first_name": "Heather",
        "last_name": "White",
        "email": "chad78@example.com"
    },
    {
        "first_name": "Stacey",
        "last_name": "Wilkerson",
        "email": "georgelopez@example.net"
    },
    {
        "first_name": "Adrian",
        "last_name": "Williams",
        "email": "xhenry@example.net"
    },
    {
        "first_name": "Charles",
        "last_name": "Wilson",
        "email": "paynesteven@example.com"
    },
    {
        "first_name": "Jordan",
        "last_name": "Wilson",
        "email": "donnaharrington@example.net"
    },
    {
        "first_name": "Jenna",
        "last_name": "Woodward",
        "email": "butlerjacob@example.com"
    },
    {
        "first_name": "Tracy",
        "last_name": "Wright",
        "email": "philliproberts@example.org"
    }
]